{"packages":{"jeremeamia/superclosure":{"0.8.0":{"name":"jeremeamia/superclosure","description":"A serializable, self-aware, super closure!","keywords":["serialize","parser","function","closure","tokenizer","serializable"],"homepage":"https://github.com/jeremeamia/super_closure","version":"0.8.0","version_normalized":"0.8.0.0","license":["MIT"],"authors":[{"name":"Jeremy Lindblom"}],"source":{"type":"git","url":"https://github.com/jeremeamia/super_closure.git","reference":"0260b4038a5fd5ff23e9ca0e27c023e564e88a09"},"dist":{"type":"zip","url":"https://api.github.com/repos/jeremeamia/super_closure/zipball/0260b4038a5fd5ff23e9ca0e27c023e564e88a09","reference":"0260b4038a5fd5ff23e9ca0e27c023e564e88a09","shasum":""},"type":"library","time":"2013-06-14T20:51:48+00:00","autoload":{"psr-0":{"SuperClosure":"src/"}},"require":{"php":">=5.3.2","jeremeamia/functionparser":"dev-master"},"abandoned":"opis/closure","uid":573868},"0.8.x-dev":{"name":"jeremeamia/superclosure","description":"A serializable, self-aware, super closure!","keywords":["serialize","parser","function","closure","tokenizer","serializable"],"homepage":"https://github.com/jeremeamia/super_closure","version":"0.8.x-dev","version_normalized":"0.8.9999999.9999999-dev","license":["MIT"],"authors":[{"name":"Jeremy Lindblom"}],"source":{"type":"git","url":"https://github.com/jeremeamia/super_closure.git","reference":"0260b4038a5fd5ff23e9ca0e27c023e564e88a09"},"dist":{"type":"zip","url":"https://api.github.com/repos/jeremeamia/super_closure/zipball/0260b4038a5fd5ff23e9ca0e27c023e564e88a09","reference":"0260b4038a5fd5ff23e9ca0e27c023e564e88a09","shasum":""},"type":"library","time":"2013-06-14T20:51:48+00:00","autoload":{"psr-0":{"SuperClosure":"src/"}},"require":{"php":">=5.3.2","jeremeamia/functionparser":"dev-master"},"abandoned":"opis/closure","uid":304587},"0.9.0":{"name":"jeremeamia/superclosure","description":"A serializable, self-aware, super closure!","keywords":["serialize","parser","function","closure","tokenizer","serializable"],"homepage":"https://github.com/jeremeamia/super_closure","version":"0.9.0","version_normalized":"0.9.0.0","license":["MIT"],"authors":[{"name":"Jeremy Lindblom"}],"source":{"type":"git","url":"https://github.com/jeremeamia/super_closure.git","reference":"9ab119cc29e6bae9bc74caf07aad6a7f4acc6556"},"dist":{"type":"zip","url":"https://api.github.com/repos/jeremeamia/super_closure/zipball/9ab119cc29e6bae9bc74caf07aad6a7f4acc6556","reference":"9ab119cc29e6bae9bc74caf07aad6a7f4acc6556","shasum":""},"type":"library","time":"2012-04-14T17:39:38+00:00","autoload":{"psr-0":{"SuperClosure":"src/"}},"require":{"php":">=5.3.2","jeremeamia/functionparser":"*"},"abandoned":"opis/closure","uid":573869},"0.9.1":{"name":"jeremeamia/superclosure","description":"Doing interesting things with closures like serialization and partial function application.","keywords":["serialize","parser","function","closure","tokenizer","serializable"],"homepage":"https://github.com/jeremeamia/super_closure","version":"0.9.1","version_normalized":"0.9.1.0","license":["MIT"],"authors":[{"name":"Jeremy Lindblom"}],"source":{"type":"git","url":"https://github.com/jeremeamia/super_closure.git","reference":"a1f74bfc0f648cf1019d496191b4d638fc564b95"},"dist":{"type":"zip","url":"https://api.github.com/repos/jeremeamia/super_closure/zipball/a1f74bfc0f648cf1019d496191b4d638fc564b95","reference":"a1f74bfc0f648cf1019d496191b4d638fc564b95","shasum":""},"type":"library","time":"2013-05-25T23:13:11+00:00","autoload":{"psr-0":{"Jeremeamia\\SuperClosure":"src/"}},"require":{"php":">=5.3.3","nikic/php-parser":"0.9.*@dev"},"require-dev":{"phpunit/phpunit":"3.7.*"},"abandoned":"opis/closure","uid":573870},"0.9.2":{"name":"jeremeamia/superclosure","description":"Doing interesting things with closures like serialization and partial function application.","keywords":["serialize","parser","function","closure","tokenizer","serializable"],"homepage":"https://github.com/jeremeamia/super_closure","version":"0.9.2","version_normalized":"0.9.2.0","license":["MIT"],"authors":[{"name":"Jeremy Lindblom"}],"source":{"type":"git","url":"https://github.com/jeremeamia/super_closure.git","reference":"2134c1674d20c10e565f73cb141991322c54c123"},"dist":{"type":"zip","url":"https://api.github.com/repos/jeremeamia/super_closure/zipball/2134c1674d20c10e565f73cb141991322c54c123","reference":"2134c1674d20c10e565f73cb141991322c54c123","shasum":""},"type":"library","time":"2013-05-26T16:46:28+00:00","autoload":{"psr-0":{"Jeremeamia\\SuperClosure":"src/"}},"require":{"php":">=5.3.3","nikic/php-parser":"dev-master"},"require-dev":{"phpunit/phpunit":"3.7.*"},"abandoned":"opis/closure","uid":573871},"1.0.0":{"name":"jeremeamia/superclosure","description":"Doing interesting things with closures like serialization and partial function application.","keywords":["serialize","parser","function","closure","tokenizer","serializable"],"homepage":"https://github.com/jeremeamia/super_closure","version":"1.0.0","version_normalized":"1.0.0.0","license":["MIT"],"authors":[{"name":"Jeremy Lindblom"}],"source":{"type":"git","url":"https://github.com/jeremeamia/super_closure.git","reference":"dba99c01800510c2d78a15d8579a49673072f270"},"dist":{"type":"zip","url":"https://api.github.com/repos/jeremeamia/super_closure/zipball/dba99c01800510c2d78a15d8579a49673072f270","reference":"dba99c01800510c2d78a15d8579a49673072f270","shasum":""},"type":"library","time":"2013-06-14T07:20:08+00:00","autoload":{"psr-0":{"Jeremeamia\\SuperClosure":"src/"}},"require":{"php":">=5.3.3","nikic/php-parser":"dev-master"},"require-dev":{"phpunit/phpunit":"3.7.*"},"abandoned":"opis/closure","uid":573872},"1.0.1":{"name":"jeremeamia/superclosure","description":"Doing interesting things with closures like serialization.","keywords":["serialize","parser","function","closure","tokenizer","serializable"],"homepage":"https://github.com/jeremeamia/super_closure","version":"1.0.1","version_normalized":"1.0.1.0","license":["MIT"],"authors":[{"name":"Jeremy Lindblom"}],"source":{"type":"git","url":"https://github.com/jeremeamia/super_closure.git","reference":"d05400085f7d4ae6f20ba30d36550836c0d061e8"},"dist":{"type":"zip","url":"https://api.github.com/repos/jeremeamia/super_closure/zipball/d05400085f7d4ae6f20ba30d36550836c0d061e8","reference":"d05400085f7d4ae6f20ba30d36550836c0d061e8","shasum":""},"type":"library","time":"2013-10-09T04:20:00+00:00","autoload":{"psr-0":{"Jeremeamia\\SuperClosure":"src/"}},"require":{"php":">=5.3.3","nikic/php-parser":"~0.9"},"require-dev":{"phpunit/phpunit":"~3.7"},"abandoned":"opis/closure","uid":573873},"1.0.2":{"name":"jeremeamia/superclosure","description":"Doing interesting things with closures like serialization.","keywords":["serialize","parser","function","closure","tokenizer","serializable"],"homepage":"https://github.com/jeremeamia/super_closure","version":"1.0.2","version_normalized":"1.0.2.0","license":["MIT"],"authors":[{"name":"Jeremy Lindblom"}],"source":{"type":"git","url":"https://github.com/jeremeamia/super_closure.git","reference":"4d89ca74994feab128ea46d5b3add92e6cb84554"},"dist":{"type":"zip","url":"https://api.github.com/repos/jeremeamia/super_closure/zipball/4d89ca74994feab128ea46d5b3add92e6cb84554","reference":"4d89ca74994feab128ea46d5b3add92e6cb84554","shasum":""},"type":"library","time":"2015-01-10T01:09:28+00:00","autoload":{"psr-0":{"Jeremeamia\\SuperClosure":"src/"}},"require":{"php":">=5.3.3","nikic/php-parser":"~0.9"},"require-dev":{"phpunit/phpunit":"~3.7"},"abandoned":"opis/closure","uid":573874},"1.0.x-dev":{"name":"jeremeamia/superclosure","description":"Doing interesting things with closures like serialization.","keywords":["serialize","parser","function","closure","tokenizer","serializable"],"homepage":"https://github.com/jeremeamia/super_closure","version":"1.0.x-dev","version_normalized":"1.0.9999999.9999999-dev","license":["MIT"],"authors":[{"name":"Jeremy Lindblom"}],"source":{"type":"git","url":"https://github.com/jeremeamia/super_closure.git","reference":"4d89ca74994feab128ea46d5b3add92e6cb84554"},"dist":{"type":"zip","url":"https://api.github.com/repos/jeremeamia/super_closure/zipball/4d89ca74994feab128ea46d5b3add92e6cb84554","reference":"4d89ca74994feab128ea46d5b3add92e6cb84554","shasum":""},"type":"library","time":"2015-01-10T01:09:28+00:00","autoload":{"psr-0":{"Jeremeamia\\SuperClosure":"src/"}},"require":{"php":">=5.3.3","nikic/php-parser":"~0.9"},"require-dev":{"phpunit/phpunit":"~3.7"},"abandoned":"opis/closure","uid":304586},"2.0-alpha1":{"name":"jeremeamia/superclosure","description":"Serialize Closures, including their context","keywords":["serialize","parser","function","closure","tokenizer","serializable","lambda"],"homepage":"https://github.com/jeremeamia/super_closure","version":"2.0-alpha1","version_normalized":"2.0.0.0-alpha1","license":["MIT"],"authors":[{"name":"Jeremy Lindblom","email":"jeremeamia@gmail.com","homepage":"http://webjeremy.com","role":"Developer"}],"source":{"type":"git","url":"https://github.com/jeremeamia/super_closure.git","reference":"9cadee5a7f22110a5d133c6ef16aa81bbc58efbd"},"dist":{"type":"zip","url":"https://api.github.com/repos/jeremeamia/super_closure/zipball/9cadee5a7f22110a5d133c6ef16aa81bbc58efbd","reference":"9cadee5a7f22110a5d133c6ef16aa81bbc58efbd","shasum":""},"type":"library","time":"2014-01-14T02:20:36+00:00","autoload":{"files":["autoload.php","src/functions.php"]},"require":{"php":">=5.3.3","nikic/php-parser":"~0.9"},"require-dev":{"phpunit/phpunit":"~3.7"},"abandoned":"opis/closure","uid":573875},"2.0.0":{"name":"jeremeamia/superclosure","description":"Serialize Closure objects, including their context and binding","keywords":["serialize","parser","function","closure","tokenizer","serializable","lambda"],"homepage":"https://github.com/jeremeamia/super_closure","version":"2.0.0","version_normalized":"2.0.0.0","license":["MIT"],"authors":[{"name":"Jeremy Lindblom","email":"jeremeamia@gmail.com","homepage":"https://github.com/jeremeamia","role":"Developer"}],"source":{"type":"git","url":"https://github.com/jeremeamia/super_closure.git","reference":"ac4394c7e21777ac48543190fb0872b2fc7f17af"},"dist":{"type":"zip","url":"https://api.github.com/repos/jeremeamia/super_closure/zipball/ac4394c7e21777ac48543190fb0872b2fc7f17af","reference":"ac4394c7e21777ac48543190fb0872b2fc7f17af","shasum":""},"type":"library","time":"2015-01-26T23:07:39+00:00","autoload":{"psr-4":{"SuperClosure\\":"src/"}},"extra":{"branch-alias":{"dev-master":"2.0-dev"}},"require":{"php":">=5.4","nikic/php-parser":"~1.0"},"require-dev":{"phpunit/phpunit":"~4.0","codeclimate/php-test-reporter":"~0.1.2"},"abandoned":"opis/closure","uid":573878},"2.0.0-alpha2":{"name":"jeremeamia/superclosure","description":"Serialize Closures, including their context","keywords":["serialize","parser","function","closure","tokenizer","serializable","lambda"],"homepage":"https://github.com/jeremeamia/super_closure","version":"2.0.0-alpha2","version_normalized":"2.0.0.0-alpha2","license":["MIT"],"authors":[{"name":"Jeremy Lindblom","email":"jeremeamia@gmail.com","homepage":"http://webjeremy.com","role":"Developer"}],"source":{"type":"git","url":"https://github.com/jeremeamia/super_closure.git","reference":"841cdcc27fc9f06d6080c0271c6ff9281367c5f7"},"dist":{"type":"zip","url":"https://api.github.com/repos/jeremeamia/super_closure/zipball/841cdcc27fc9f06d6080c0271c6ff9281367c5f7","reference":"841cdcc27fc9f06d6080c0271c6ff9281367c5f7","shasum":""},"type":"library","time":"2014-02-05T20:44:27+00:00","autoload":{"psr-4":{"SuperClosure\\":"src/SuperClosure/"},"files":["src/functions.php"]},"require":{"php":">=5.3.3","nikic/php-parser":"~0.9"},"require-dev":{"phpunit/phpunit":"~3.7"},"abandoned":"opis/closure","uid":573876},"2.0.0-beta.1":{"name":"jeremeamia/superclosure","description":"Serialize Closures, including their context","keywords":["serialize","parser","function","closure","tokenizer","serializable","lambda"],"homepage":"https://github.com/jeremeamia/super_closure","version":"2.0.0-beta.1","version_normalized":"2.0.0.0-beta1","license":["MIT"],"authors":[{"name":"Jeremy Lindblom","email":"jeremeamia@gmail.com","homepage":"http://webjeremy.com","role":"Developer"}],"source":{"type":"git","url":"https://github.com/jeremeamia/super_closure.git","reference":"6e3d85600b6f6953aa6a5c3decafb50198c15d5a"},"dist":{"type":"zip","url":"https://api.github.com/repos/jeremeamia/super_closure/zipball/6e3d85600b6f6953aa6a5c3decafb50198c15d5a","reference":"6e3d85600b6f6953aa6a5c3decafb50198c15d5a","shasum":""},"type":"library","time":"2015-01-19T18:52:43+00:00","autoload":{"psr-4":{"SuperClosure\\":"src/"}},"extra":{"branch-alias":{"dev-master":"2.0-dev"}},"require":{"php":">=5.4","nikic/php-parser":"~1.0"},"require-dev":{"phpunit/phpunit":"~4.0"},"abandoned":"opis/closure","uid":573877},"2.0.x-dev":{"name":"jeremeamia/superclosure","description":"Serialize Closure objects, including their context and binding","keywords":["serialize","parser","function","closure","tokenizer","serializable","lambda"],"homepage":"https://github.com/jeremeamia/super_closure","version":"2.0.x-dev","version_normalized":"2.0.9999999.9999999-dev","license":["MIT"],"authors":[{"name":"Jeremy Lindblom","email":"jeremeamia@gmail.com","homepage":"https://github.com/jeremeamia","role":"Developer"}],"source":{"type":"git","url":"https://github.com/jeremeamia/super_closure.git","reference":"ac4394c7e21777ac48543190fb0872b2fc7f17af"},"dist":{"type":"zip","url":"https://api.github.com/repos/jeremeamia/super_closure/zipball/ac4394c7e21777ac48543190fb0872b2fc7f17af","reference":"ac4394c7e21777ac48543190fb0872b2fc7f17af","shasum":""},"type":"library","time":"2015-01-26T23:07:39+00:00","autoload":{"psr-4":{"SuperClosure\\":"src/"}},"extra":{"branch-alias":{"dev-master":"2.0-dev"}},"require":{"php":">=5.4","nikic/php-parser":"~1.0"},"require-dev":{"phpunit/phpunit":"~4.0","codeclimate/php-test-reporter":"~0.1.2"},"abandoned":"opis/closure","uid":565966},"2.1.0":{"name":"jeremeamia/superclosure","description":"Serialize Closure objects, including their context and binding","keywords":["serialize","parser","function","closure","tokenizer","serializable","lambda"],"homepage":"https://github.com/jeremeamia/super_closure","version":"2.1.0","version_normalized":"2.1.0.0","license":["MIT"],"authors":[{"name":"Jeremy Lindblom","email":"jeremeamia@gmail.com","homepage":"https://github.com/jeremeamia","role":"Developer"}],"source":{"type":"git","url":"https://github.com/jeremeamia/super_closure.git","reference":"b712f39c671e5ead60c7ebfe662545456aade833"},"dist":{"type":"zip","url":"https://api.github.com/repos/jeremeamia/super_closure/zipball/b712f39c671e5ead60c7ebfe662545456aade833","reference":"b712f39c671e5ead60c7ebfe662545456aade833","shasum":""},"type":"library","time":"2015-03-11T20:06:43+00:00","autoload":{"psr-4":{"SuperClosure\\":"src/"}},"extra":{"branch-alias":{"dev-master":"2.1-dev"}},"require":{"php":">=5.4","nikic/php-parser":"~1.0"},"require-dev":{"phpunit/phpunit":"~4.0","codeclimate/php-test-reporter":"~0.1.2"},"abandoned":"opis/closure","uid":573879},"2.1.x-dev":{"name":"jeremeamia/superclosure","description":"Serialize Closure objects, including their context and binding","keywords":["serialize","parser","function","closure","tokenizer","serializable","lambda"],"homepage":"https://github.com/jeremeamia/super_closure","version":"2.1.x-dev","version_normalized":"2.1.9999999.9999999-dev","license":["MIT"],"authors":[{"name":"Jeremy Lindblom","email":"jeremeamia@gmail.com","homepage":"https://github.com/jeremeamia","role":"Developer"}],"source":{"type":"git","url":"https://github.com/jeremeamia/super_closure.git","reference":"b712f39c671e5ead60c7ebfe662545456aade833"},"dist":{"type":"zip","url":"https://api.github.com/repos/jeremeamia/super_closure/zipball/b712f39c671e5ead60c7ebfe662545456aade833","reference":"b712f39c671e5ead60c7ebfe662545456aade833","shasum":""},"type":"library","time":"2015-03-11T20:06:43+00:00","autoload":{"psr-4":{"SuperClosure\\":"src/"}},"extra":{"branch-alias":{"dev-master":"2.1-dev"}},"require":{"php":">=5.4","nikic/php-parser":"~1.0"},"require-dev":{"phpunit/phpunit":"~4.0","codeclimate/php-test-reporter":"~0.1.2"},"abandoned":"opis/closure","uid":565967},"2.2.0":{"name":"jeremeamia/superclosure","description":"Serialize Closure objects, including their context and binding","keywords":["serialize","parser","function","closure","tokenizer","serializable","lambda"],"homepage":"https://github.com/jeremeamia/super_closure","version":"2.2.0","version_normalized":"2.2.0.0","license":["MIT"],"authors":[{"name":"Jeremy Lindblom","email":"jeremeamia@gmail.com","homepage":"https://github.com/jeremeamia","role":"Developer"}],"source":{"type":"git","url":"https://github.com/jeremeamia/super_closure.git","reference":"29a88be2a4846d27c1613aed0c9071dfad7b5938"},"dist":{"type":"zip","url":"https://api.github.com/repos/jeremeamia/super_closure/zipball/29a88be2a4846d27c1613aed0c9071dfad7b5938","reference":"29a88be2a4846d27c1613aed0c9071dfad7b5938","shasum":""},"type":"library","time":"2015-12-05T17:17:57+00:00","autoload":{"psr-4":{"SuperClosure\\":"src/"}},"extra":{"branch-alias":{"dev-master":"2.2-dev"}},"require":{"php":">=5.4","nikic/php-parser":"^1.2|^2.0","symfony/polyfill-php56":"^1.0"},"require-dev":{"phpunit/phpunit":"^4.0|^5.0"},"abandoned":"opis/closure","uid":610433},"2.2.x-dev":{"name":"jeremeamia/superclosure","description":"Serialize Closure objects, including their context and binding","keywords":["serialize","parser","function","closure","tokenizer","serializable","lambda"],"homepage":"https://github.com/jeremeamia/super_closure","version":"2.2.x-dev","version_normalized":"2.2.9999999.9999999-dev","license":["MIT"],"authors":[{"name":"Jeremy Lindblom","email":"jeremeamia@gmail.com","homepage":"https://github.com/jeremeamia","role":"Developer"}],"source":{"type":"git","url":"https://github.com/jeremeamia/super_closure.git","reference":"29a88be2a4846d27c1613aed0c9071dfad7b5938"},"dist":{"type":"zip","url":"https://api.github.com/repos/jeremeamia/super_closure/zipball/29a88be2a4846d27c1613aed0c9071dfad7b5938","reference":"29a88be2a4846d27c1613aed0c9071dfad7b5938","shasum":""},"type":"library","time":"2015-12-05T17:17:57+00:00","autoload":{"psr-4":{"SuperClosure\\":"src/"}},"extra":{"branch-alias":{"dev-master":"2.2-dev"}},"require":{"php":">=5.4","nikic/php-parser":"^1.2|^2.0","symfony/polyfill-php56":"^1.0"},"require-dev":{"phpunit/phpunit":"^4.0|^5.0"},"abandoned":"opis/closure","uid":1115874},"2.3.0":{"name":"jeremeamia/superclosure","description":"Serialize Closure objects, including their context and binding","keywords":["serialize","parser","function","closure","tokenizer","serializable","lambda"],"homepage":"https://github.com/jeremeamia/super_closure","version":"2.3.0","version_normalized":"2.3.0.0","license":["MIT"],"authors":[{"name":"Jeremy Lindblom","email":"jeremeamia@gmail.com","homepage":"https://github.com/jeremeamia","role":"Developer"}],"source":{"type":"git","url":"https://github.com/jeremeamia/super_closure.git","reference":"443c3df3207f176a1b41576ee2a66968a507b3db"},"dist":{"type":"zip","url":"https://api.github.com/repos/jeremeamia/super_closure/zipball/443c3df3207f176a1b41576ee2a66968a507b3db","reference":"443c3df3207f176a1b41576ee2a66968a507b3db","shasum":""},"type":"library","time":"2016-12-07T09:37:55+00:00","autoload":{"psr-4":{"SuperClosure\\":"src/"}},"extra":{"branch-alias":{"dev-master":"2.3-dev"}},"require":{"php":">=5.4","nikic/php-parser":"^1.2|^2.0|^3.0","symfony/polyfill-php56":"^1.0"},"require-dev":{"phpunit/phpunit":"^4.0|^5.0"},"abandoned":"opis/closure","uid":1116004},"2.3.x-dev":{"name":"jeremeamia/superclosure","description":"Serialize Closure objects, including their context and binding","keywords":["serialize","parser","function","closure","tokenizer","serializable","lambda"],"homepage":"https://github.com/jeremeamia/super_closure","version":"2.3.x-dev","version_normalized":"2.3.9999999.9999999-dev","license":["MIT"],"authors":[{"name":"Jeremy Lindblom","email":"jeremeamia@gmail.com","homepage":"https://github.com/jeremeamia","role":"Developer"}],"source":{"type":"git","url":"https://github.com/jeremeamia/super_closure.git","reference":"443c3df3207f176a1b41576ee2a66968a507b3db"},"dist":{"type":"zip","url":"https://api.github.com/repos/jeremeamia/super_closure/zipball/443c3df3207f176a1b41576ee2a66968a507b3db","reference":"443c3df3207f176a1b41576ee2a66968a507b3db","shasum":""},"type":"library","time":"2016-12-07T09:37:55+00:00","autoload":{"psr-4":{"SuperClosure\\":"src/"}},"extra":{"branch-alias":{"dev-master":"2.3-dev"}},"require":{"php":">=5.4","nikic/php-parser":"^1.2|^2.0|^3.0","symfony/polyfill-php56":"^1.0"},"require-dev":{"phpunit/phpunit":"^4.0|^5.0"},"abandoned":"opis/closure","uid":2017102},"2.4.0":{"name":"jeremeamia/superclosure","description":"Serialize Closure objects, including their context and binding","keywords":["serialize","parser","function","closure","tokenizer","serializable","lambda"],"homepage":"https://github.com/jeremeamia/super_closure","version":"2.4.0","version_normalized":"2.4.0.0","license":["MIT"],"authors":[{"name":"Jeremy Lindblom","email":"jeremeamia@gmail.com","homepage":"https://github.com/jeremeamia","role":"Developer"}],"source":{"type":"git","url":"https://github.com/jeremeamia/super_closure.git","reference":"5707d5821b30b9a07acfb4d76949784aaa0e9ce9"},"dist":{"type":"zip","url":"https://api.github.com/repos/jeremeamia/super_closure/zipball/5707d5821b30b9a07acfb4d76949784aaa0e9ce9","reference":"5707d5821b30b9a07acfb4d76949784aaa0e9ce9","shasum":""},"type":"library","time":"2018-03-21T22:21:57+00:00","autoload":{"psr-4":{"SuperClosure\\":"src/"}},"extra":{"branch-alias":{"dev-master":"2.4-dev"}},"require":{"php":">=5.4","nikic/php-parser":"^1.2|^2.0|^3.0|^4.0","symfony/polyfill-php56":"^1.0"},"require-dev":{"phpunit/phpunit":"^4.0|^5.0"},"abandoned":"opis/closure","uid":2017106},"dev-master":{"name":"jeremeamia/superclosure","description":"Serialize Closure objects, including their context and binding","keywords":["serialize","parser","function","closure","tokenizer","serializable","lambda"],"homepage":"https://github.com/jeremeamia/super_closure","version":"dev-master","version_normalized":"9999999-dev","license":["MIT"],"authors":[{"name":"Jeremy Lindblom","email":"jeremeamia@gmail.com","homepage":"https://github.com/jeremeamia","role":"Developer"}],"source":{"type":"git","url":"https://github.com/jeremeamia/super_closure.git","reference":"5b3c76c0e4c6b01cddb6e997f579a1b4c59ee8a0"},"dist":{"type":"zip","url":"https://api.github.com/repos/jeremeamia/super_closure/zipball/5b3c76c0e4c6b01cddb6e997f579a1b4c59ee8a0","reference":"5b3c76c0e4c6b01cddb6e997f579a1b4c59ee8a0","shasum":""},"type":"library","time":"2021-03-29T15:20:09+00:00","autoload":{"psr-4":{"SuperClosure\\":"src/"}},"extra":{"branch-alias":{"dev-master":"2.4-dev"}},"default-branch":true,"require":{"php":">=5.4","nikic/php-parser":"^1.2|^2.0|^3.0|^4.0","symfony/polyfill-php56":"^1.0"},"require-dev":{"phpunit/phpunit":"^4.0|^5.0"},"abandoned":"opis/closure","uid":5063143}},"kesselb/nextcloud-3rdparty":{"20.0.0":{"name":"kesselb/nextcloud-3rdparty","description":"","keywords":[],"homepage":"","version":"20.0.0","version_normalized":"20.0.0.0","license":["MIT"],"authors":[],"source":{"type":"git","url":"https://github.com/kesselb/nextcloud-3rdparty.git","reference":"e0b9fa9e68071f4eb3d8d4c940160e8383f4a306"},"dist":{"type":"zip","url":"https://api.github.com/repos/kesselb/nextcloud-3rdparty/zipball/e0b9fa9e68071f4eb3d8d4c940160e8383f4a306","reference":"e0b9fa9e68071f4eb3d8d4c940160e8383f4a306","shasum":""},"type":"metapackage","time":"2021-01-10T17:07:41+00:00","require":{"php":">=7.2"},"replace":{"aws/aws-sdk-php":"3.133.27","bantu/ini-get-wrapper":"v1.0.1","beberlei/assert":"v3.2.7","christophwurst/id3parser":"v0.1.1","deepdiver/zipstreamer":"1.1.1","deepdiver1975/tarstreamer":"2.0.0","doctrine/annotations":"v1.6.0","doctrine/cache":"1.10.1","doctrine/collections":"v1.5.0","doctrine/common":"v2.10.0","doctrine/dbal":"2.10.2","doctrine/event-manager":"1.1.0","doctrine/inflector":"v1.3.0","doctrine/lexer":"1.2.0","doctrine/persistence":"v1.1.0","doctrine/reflection":"v1.0.0","egulias/email-validator":"2.1.11","fgrosse/phpasn1":"v2.1.1","guzzlehttp/guzzle":"6.5.2","guzzlehttp/promises":"v1.3.1","guzzlehttp/psr7":"1.6.1","guzzlehttp/ringphp":"1.1.0","guzzlehttp/streams":"3.0.0","icewind/searchdav":"v2.0.0","icewind/streams":"v0.7.1","jeremeamia/superclosure":"2.4.0","justinrainbow/json-schema":"5.2.9","league/flysystem":"1.0.64","league/uri":"6.2.1","league/uri-components":"2.2.1","league/uri-interfaces":"2.1.0","microsoft/azure-storage-blob":"1.5.0","microsoft/azure-storage-common":"1.4.1","mtdowling/jmespath.php":"2.5.0","nextcloud/lognormalizer":"v1.0.0","nikic/php-parser":"v4.3.0","paragonie/random_compat":"v9.99.99","patchwork/jsqueeze":"v2.0.5","patchwork/utf8":"v1.3.1","pear/archive_tar":"1.4.11","pear/console_getopt":"v1.4.3","pear/pear-core-minimal":"v1.10.10","pear/pear_exception":"v1.0.1","php-http/guzzle6-adapter":"v2.0.1","php-http/httplug":"2.1.0","php-http/promise":"v1.0.0","php-opencloud/openstack":"v3.0.7","phpseclib/phpseclib":"2.0.25","pimple/pimple":"v3.2.3","psr/container":"1.0.0","psr/http-client":"1.0.0","psr/http-factory":"1.0.1","psr/http-message":"1.0.1","psr/log":"1.1.0","punic/punic":"1.6.5","ralouphie/getallheaders":"3.0.3","ramsey/uuid":"3.9.3","react/promise":"v2.2.1","sabre/dav":"4.0.3","sabre/event":"5.1.0","sabre/http":"5.1.0","sabre/uri":"2.2.0","sabre/vobject":"4.3.0","sabre/xml":"2.2.3","scssphp/scssphp":"1.0.3","spomky-labs/base64url":"v2.0.1","spomky-labs/cbor-php":"v1.0.8","stecman/symfony-console-completion":"0.11.0","swiftmailer/swiftmailer":"v6.2.3","symfony/console":"v4.4.10","symfony/event-dispatcher":"v4.4.10","symfony/polyfill-ctype":"v1.15.0","symfony/polyfill-iconv":"v1.12.0","symfony/polyfill-intl-idn":"v1.12.0","symfony/polyfill-mbstring":"v1.14.0","symfony/polyfill-php56":"v1.10.0","symfony/polyfill-php72":"v1.12.0","symfony/polyfill-php73":"v1.13.1","symfony/polyfill-php80":"v1.17.1","symfony/polyfill-util":"v1.10.0","symfony/process":"v4.4.10","symfony/routing":"v4.4.10","symfony/translation":"v4.4.10","web-auth/cose-lib":"v3.1.1","web-auth/metadata-service":"v3.1.1","web-auth/webauthn-lib":"v3.1.1"},"uid":4825635},"dev-stable20":{"name":"kesselb/nextcloud-3rdparty","description":"","keywords":[],"homepage":"","version":"dev-stable20","version_normalized":"dev-stable20","license":["MIT"],"authors":[],"source":{"type":"git","url":"https://github.com/kesselb/nextcloud-3rdparty.git","reference":"e0b9fa9e68071f4eb3d8d4c940160e8383f4a306"},"dist":{"type":"zip","url":"https://api.github.com/repos/kesselb/nextcloud-3rdparty/zipball/e0b9fa9e68071f4eb3d8d4c940160e8383f4a306","reference":"e0b9fa9e68071f4eb3d8d4c940160e8383f4a306","shasum":""},"type":"metapackage","time":"2021-01-10T17:07:41+00:00","require":{"php":">=7.2"},"replace":{"aws/aws-sdk-php":"3.133.27","bantu/ini-get-wrapper":"v1.0.1","beberlei/assert":"v3.2.7","christophwurst/id3parser":"v0.1.1","deepdiver/zipstreamer":"1.1.1","deepdiver1975/tarstreamer":"2.0.0","doctrine/annotations":"v1.6.0","doctrine/cache":"1.10.1","doctrine/collections":"v1.5.0","doctrine/common":"v2.10.0","doctrine/dbal":"2.10.2","doctrine/event-manager":"1.1.0","doctrine/inflector":"v1.3.0","doctrine/lexer":"1.2.0","doctrine/persistence":"v1.1.0","doctrine/reflection":"v1.0.0","egulias/email-validator":"2.1.11","fgrosse/phpasn1":"v2.1.1","guzzlehttp/guzzle":"6.5.2","guzzlehttp/promises":"v1.3.1","guzzlehttp/psr7":"1.6.1","guzzlehttp/ringphp":"1.1.0","guzzlehttp/streams":"3.0.0","icewind/searchdav":"v2.0.0","icewind/streams":"v0.7.1","jeremeamia/superclosure":"2.4.0","justinrainbow/json-schema":"5.2.9","league/flysystem":"1.0.64","league/uri":"6.2.1","league/uri-components":"2.2.1","league/uri-interfaces":"2.1.0","microsoft/azure-storage-blob":"1.5.0","microsoft/azure-storage-common":"1.4.1","mtdowling/jmespath.php":"2.5.0","nextcloud/lognormalizer":"v1.0.0","nikic/php-parser":"v4.3.0","paragonie/random_compat":"v9.99.99","patchwork/jsqueeze":"v2.0.5","patchwork/utf8":"v1.3.1","pear/archive_tar":"1.4.11","pear/console_getopt":"v1.4.3","pear/pear-core-minimal":"v1.10.10","pear/pear_exception":"v1.0.1","php-http/guzzle6-adapter":"v2.0.1","php-http/httplug":"2.1.0","php-http/promise":"v1.0.0","php-opencloud/openstack":"v3.0.7","phpseclib/phpseclib":"2.0.25","pimple/pimple":"v3.2.3","psr/container":"1.0.0","psr/http-client":"1.0.0","psr/http-factory":"1.0.1","psr/http-message":"1.0.1","psr/log":"1.1.0","punic/punic":"1.6.5","ralouphie/getallheaders":"3.0.3","ramsey/uuid":"3.9.3","react/promise":"v2.2.1","sabre/dav":"4.0.3","sabre/event":"5.1.0","sabre/http":"5.1.0","sabre/uri":"2.2.0","sabre/vobject":"4.3.0","sabre/xml":"2.2.3","scssphp/scssphp":"1.0.3","spomky-labs/base64url":"v2.0.1","spomky-labs/cbor-php":"v1.0.8","stecman/symfony-console-completion":"0.11.0","swiftmailer/swiftmailer":"v6.2.3","symfony/console":"v4.4.10","symfony/event-dispatcher":"v4.4.10","symfony/polyfill-ctype":"v1.15.0","symfony/polyfill-iconv":"v1.12.0","symfony/polyfill-intl-idn":"v1.12.0","symfony/polyfill-mbstring":"v1.14.0","symfony/polyfill-php56":"v1.10.0","symfony/polyfill-php72":"v1.12.0","symfony/polyfill-php73":"v1.13.1","symfony/polyfill-php80":"v1.17.1","symfony/polyfill-util":"v1.10.0","symfony/process":"v4.4.10","symfony/routing":"v4.4.10","symfony/translation":"v4.4.10","web-auth/cose-lib":"v3.1.1","web-auth/metadata-service":"v3.1.1","web-auth/webauthn-lib":"v3.1.1"},"uid":4825532}}}}